ruff_quickfix/__init__.py
ruff_quickfix/__main__.py
ruff_quickfix/cli.py
ruff_quickfix/lint.py
ruff_quickfix/py.typed
ruff_quickfix-0.2.1.dist-info/LICENSE
ruff_quickfix-0.2.1.dist-info/METADATA
ruff_quickfix-0.2.1.dist-info/WHEEL
ruff_quickfix-0.2.1.dist-info/entry_points.txt
ruff_quickfix-0.2.1.dist-info/RECORD
