Metadata-Version: 2.3
Name: ruff-quickfix
Version: 0.2.1
Summary: Wrapper for the `ruff` command for (neo)vim's quickfix
License: LICENSE
Keywords: ruff,cli,vim,neovim,nvim,quickfix
Author: Neal Joslin
Author-email: neal@joslin.io
Requires-Python: >=3.8,<4.0
Classifier: License :: Other/Proprietary License
Classifier: Programming Language :: Python :: 3
Classifier: Programming Language :: Python :: 3.8
Classifier: Programming Language :: Python :: 3.9
Classifier: Programming Language :: Python :: 3.10
Classifier: Programming Language :: Python :: 3.11
Classifier: Programming Language :: Python :: 3.12
Classifier: Programming Language :: Python :: 3.13
Provides-Extra: ruff
Requires-Dist: click (>=8.1.7,<9.0.0)
Requires-Dist: ruff (>=0.6.1,<0.7.0) ; extra == "ruff"
Project-URL: Repository, https://github.com/Nealium/ruff-quickfix
